Workbook

Sheet Инструкция
A1: АНР-модель выбора поставщиков оборудования для диспетчерских комплексов (практика № 2)
A2: АНР - метод анализа иерархий: критерии сравниваются попарно по шкале Саати 1-9, из матрицы получаются веса.
A3: Обозначения цветом:
A4: жёлтая ячейка, синий текст - суждение ЛПР (можно менять, лист «Критерии», верхний треугольник матрицы);
A5: синий текст - исходные данные (цены, сроки, оценки 1-5) и значения, рассчитанные в Python;
A6: зелёный текст - ссылка на другой лист; чёрный текст - формула.
A7: Шкала Саати: 1 - равная важность, 3 - умеренное превосходство, 5 - существенное, 7 - значительное, 9 - абсолютное; 2, 4, 6, 8 - промежуточные; обратные дроби - если важнее второй критерий.
A8: ИС - индекс согласованности, СИ - случайный индекс Саати, ОС - отношение согласованности = ИС / СИ; суждения согласованы при ОС ≤ 0,10.
A9: Локальные приоритеты альтернатив рассчитаны в Python (scripts/p2_ahp.py) по матрицам парных сравнений альтернатив; пример такой матрицы на формулах - лист «Пример_ИБП_k1».
A10: Оценки 1-5 (качество, надёжность, санкционный риск, происхождение) - экспертные оценки аналитика по правилам из открытых сведений (sppr/ratings.py, config/quality_ratings.json).
A11: Пример изменения: если директор считает стоимость в 3 раза важнее качества, введите 3 в ячейку «k1 / k2» - веса, ОС и ранги пересчитаются.

Sheet Критерии
A1: Матрица парных сравнений критериев (шкала Саати 1-9)
A2: Жёлтые ячейки - суждения ЛПР; нижний треугольник = 1 / верхний.
A3: Критерий | B3: k1 | C3: k2 | D3: k3 | E3: k4 | F3: k5 | G3: k6 | H3: k7 | I3: Среднее геометрическое строки | J3: Вес w | K3: (A·w) | L3: (A·w) / w | M3: Вес (Python, собств. вектор)
A4: k1 Стоимость закупки | B4: 1 | C4: 2 | D4: 1 | E4: 2 | F4: 3 | G4: 1 | H4: 3 | I4: =PRODUCT(B4:H4)^(1/7) -> 1.6685104 | J4: =I4/SUM($I$4:$I$10) -> 0.21314436 | K4: =B4*$J$4+C4*$J$5+D4*$J$6+E4*$J$7+F4*$J$8+G4*$J$9+H4*$J$10 -> 1.5207998 | L4: =K4/J4 -> 7.1350694 | M4: 0.2143
A5: k2 Качество и технический уровень | B5: =1/C4 -> 0.5 | C5: 1 | D5: 0.5 | E5: 2 | F5: 3 | G5: 1 | H5: 2 | I5: =PRODUCT(B5:H5)^(1/7) -> 1.1699308 | J5: =I5/SUM($I$4:$I$10) -> 0.14945316 | K5: =B5*$J$4+C5*$J$5+D5*$J$6+E5*$J$7+F5*$J$8+G5*$J$9+H5*$J$10 -> 1.0691994 | L5: =K5/J5 -> 7.1540768 | M5: 0.1505
A6: k3 Надёжность поставщика | B6: =1/D4 -> 1 | C6: =1/D5 -> 2 | D6: 1 | E6: 2 | F6: 4 | G6: 1 | H6: 3 | I6: =PRODUCT(B6:H6)^(1/7) -> 1.7385105 | J6: =I6/SUM($I$4:$I$10) -> 0.22208654 | K6: =B6*$J$4+C6*$J$5+D6*$J$6+E6*$J$7+F6*$J$8+G6*$J$9+H6*$J$10 -> 1.5744841 | L6: =K6/J6 -> 7.0895071 | M6: 0.2219
A7: k4 Срок поставки | B7: =1/E4 -> 0.5 | C7: =1/E5 -> 0.5 | D7: =1/E6 -> 0.5 | E7: 1 | F7: 2 | G7: 0.5 | H7: 1 | I7: =PRODUCT(B7:H7)^(1/7) -> 0.74299714 | J7: =I7/SUM($I$4:$I$10) -> 0.094914389 | K7: =B7*$J$4+C7*$J$5+D7*$J$6+E7*$J$7+F7*$J$8+G7*$J$9+H7*$J$10 -> 0.67024955 | L7: =K7/J7 -> 7.0616221 | M7: 0.0944
A8: k5 Гарантия и сервис в РФ | B8: =1/F4 -> 0.33333333 | C8: =1/F5 -> 0.33333333 | D8: =1/F6 -> 0.25 | E8: =1/F7 -> 0.5 | F8: 1 | G8: 0.33333333 | H8: 0.5 | I8: =PRODUCT(B8:H8)^(1/7) -> 0.42024477 | J8: =I8/SUM($I$4:$I$10) -> 0.053684292 | K8: =B8*$J$4+C8*$J$5+D8*$J$6+E8*$J$7+F8*$J$8+G8*$J$9+H8*$J$10 -> 0.38052335 | L8: =K8/J8 -> 7.0881693 | M8: 0.0536
A9: k6 Санкционный риск канала | B9: =1/G4 -> 1 | C9: =1/G5 -> 1 | D9: =1/G6 -> 1 | E9: =1/G7 -> 2 | F9: =1/G8 -> 3 | G9: 1 | H9: 2 | I9: =PRODUCT(B9:H9)^(1/7) -> 1.4261616 | J9: =I9/SUM($I$4:$I$10) -> 0.18218544 | K9: =B9*$J$4+C9*$J$5+D9*$J$6+E9*$J$7+F9*$J$8+G9*$J$9+H9*$J$10 -> 1.2868148 | L9: =K9/J9 -> 7.0632144 | M9: 0.1812
A10: k7 Российское происхождение | B10: =1/H4 -> 0.33333333 | C10: =1/H5 -> 0.5 | D10: =1/H6 -> 0.33333333 | E10: =1/H7 -> 1 | F10: =1/H8 -> 2 | G10: =1/H9 -> 0.5 | H10: 1 | I10: =PRODUCT(B10:H10)^(1/7) -> 0.66172167 | J10: =I10/SUM($I$4:$I$10) -> 0.08453183 | K10: =B10*$J$4+C10*$J$5+D10*$J$6+E10*$J$7+F10*$J$8+G10*$J$9+H10*$J$10 -> 0.59771107 | L10: =K10/J10 -> 7.0708403 | M10: 0.0841
A12: n (число критериев) | B12: 7
A13: λmax = среднее (A·w)/w | B13: =AVERAGE(L4:L10) -> 7.0946428
A14: ИС = (λmax - n) / (n - 1) | B14: =(B13-B12)/(B12-1) -> 0.015773794
A15: СИ (случайный индекс Саати для n = 7) | B15: 1.32
A16: ОС = ИС / СИ | B16: =B14/B15 -> 0.011949844
A17: Вывод | B17: =IF(B16<=0.1,"суждения согласованы (ОС ≤ 0,10)","пересмотреть суждения (ОС > 0,10)") -> суждения согласованы (ОС ≤ 0,10)

Sheet Данные
A1: Исходные данные по альтернативам (открытые источники; оценки 1-5 - экспертные оценки аналитика)
A3: Категория | B3: Поставщик | C3: Модель | D3: k1 Цена, ₽ | E3: k2 Качество, 1-5 | F3: k3 Надёжность, 1-5 | G3: k4 Срок, нед. | H3: k5 Гарантия, мес. | I3: k6 Санкц. риск, 1-5 | J3: k7 Происхождение, 1-5 | K3: Статус цены | L3: Источник цены | M3: Оговорки
A4: ИБП | B4: APC | C4: Smart-UPS SRT 3000VA RM SRT3000RMXLI-NC | D4: 389565 | E4: 5 | F4: 4 | G4: 1 | H4: 6 | I4: 4 | J4: 1 | K4: verified_2026-10-13 | L4: https://www.tfk.ru/products/accessories/power-supplies/ups/ups-for-servers/srt3000rmxli-nc.html | M4: Цена для организаций/при оплате СБП; в заголовке страницы 395 810, на странице также 393 500 как неактуальная. Дата поступления сдвинулась с 09.10 на 16.10. Гарантия только продавца (6 мес). Сменная АКБ APCRBC152 отдельно 92 337–93 270 руб., ожидание от 10 недель. В 3,6–5 раз дороже российских аналогов.
A5: ИБП | B5: Vertiv | C5: Liebert GXT5-3000IRT2UXLE | D5: 106724 | E5: 5 | F5: 1 | G5: 12 | H5: 24 | I5: 3 | J5: 1 | K5: verified_2026-10-13 | L5: https://www.kns.ru/product/ibp-liebert-gxt5-3000irt2uxle/ | M5: Фактически недоступен к покупке: цена на странице последняя известная. Гарантия 24 мес по странице vertiv.com/ru-emea от 03.10 (страница отвечала «not available for your location»), актуальность не подтверждена. Официального заявления Vertiv о статусе в РФ не найдено.
A6: ИБП | B6: Eltena | C6: Monolith E3000RTLT (EN-ME-3000RTLT) + батарейный блок BFR96-9E | D6: 113844 | E6: 4 | F6: 5 | G6: 1 | H6: 24 | I6: 1 | J6: 3 | K6: estimate | L6: https://www.beloten.ru/ibp/ibp-eltena-monolith-e3000rtlt-2u-2400vt-vneshnie-akb-96v-zu-1-6a/ | M6: ЦЕНА НЕПОЛНАЯ: 72 310 = только ИБП. Версии 3000 ВА со встроенными АКБ у серии Monolith E нет (eltena.com: E3000RTLT и E2000RTLT). Цена блока BFR96-9E на открытой странице не найдена = not_found; в сниппетах поиска 36 522–36 880 руб. (не верифицировано). Ориентир суммы ИБП+АКБ ≈108,8–109,2 тыс. руб. НЕ верифицирован. Российский вендор, но производство OEM в Китае. 03.10 у UPS-Mag было 68 947 и гарантия 12 мес; сегодня UPS-Mag не открылся (таймаут).
A7: ИБП | B7: Piton | C7: PitON РТ-серия 3kVA с АКБ 9Ач (5 лет), РТ0030.008.002 | D7: 79950 | E7: 4 | F7: 5 | G7: 1 | H7: 24 | I7: 1 | J7: 4 | K7: verified_2026-10-13 | L7: https://piton-ups.ru/istochniki-besperebojnogo-pitaniya-ibp/odnofaznye-ibp-seriya-rt | M7: Цена со страницы серии на piton-ups.ru (бренд PITUPS, юрлицо не указано; сайт пишет, что цены носят ознакомительный характер); старая цена 138 050. Ссылка карточки содержит «bez-akb» при названии «с АКБ»: комплектацию уточнить. Гарантия 24 мес взята с UPS-Mag от 03.10 для версии без АКБ, на piton-ups.ru срок не указан. Там же: РТ0030.008.000 без АКБ 53 783; новая модель РТ003Н.006.205 3кВА/3кВт с АКБ 6×9 Ач 53 210; батарейный модуль РТВ0030.008.002 41 534.
A8: АВР | B8: Elemy | C8: ATS-1603 | D8: 60000 | E8: 4 | F8: 4 | G8: 3 | H8: 24 | I8: 1 | J8: 4 | K8: verified_2026-10-13 | L8: https://www.elemy.ru/ats-1603 | M8: Выбрана как ближайшая по функциям к Уралэнерготел и BONPET: без SNMP/Web. Расширенная гарантия до 4 лет. Реестр Минпромторга производитель заявляет только для ATS-2001, для ATS-1603 не заявлен. Вариант с SNMP/Modbus ATS-1204/16: 125 000 руб., в наличии 4 шт, гарантия 24 мес (shop.nag.ru, 13.10).
A9: АВР | B9: Уралэнерготел | C9: АВР19-16А-4 (NA04190316) | D9: 37240.5 | E9: 2 | F9: 5 | G9: 1 | H9: 12 | I9: 1 | J9: 4 | K9: verified_2026-10-13 | L9: https://uralenergotel.ru/product/ubox-avr-16-4 | M9: Цена 13.10 подтверждена только заголовком страницы («от 37 240,5 руб.»): страница рендерится скриптом, WebFetch дважды не дождался ответа. НДС, наличие, гарантия взяты из снимка 03.10. Переключение 45–55 мс медленнее электронных АВР (6–20 мс): для ИТ-нагрузки без ИБП это существенно.
A10: АВР | B10: BONPET | C10: АВР-Б-63-2-1 (щитовой шкаф) | D10: 88024 | E10: 3 | F10: 4 | G10: 2 | H10: 12 | I10: 1 | J10: 4 | K10: snapshot_2026-10-03 | L10: https://bonpet.tech/product/avr-b-63-2-1 | M10: ИНОЙ КЛАСС: не стоечный 16 А, а щитовой трёхфазный 63 А. Поиск 13.10 стоечного/16 А варианта BONPET ничего не дал. 13.10 страницу не перепроверял (бюджет), цена из снимка. Срок «от 12 дней» переведён в 2 недели.
A11: КВМ | B11: Aten | C11: CS1924M-AT-G | D11: 72119 | E11: 4 | F11: 4 | G11: 3 | H11: 12 | I11: 2 | J11: 1 | K11: verified_2026-10-13 | L11: https://www.kns.ru/product/kvm-pereklyuchatel-aten-cs1924m-at-g/ | M11: Точный аналог CS1924-AT-G (4 порта DP, без MST) без цены: atenpro.ru «Уточнить наличие» (НДС 22%, гарантия 2 года), xcom-shop «Нет в наличии». Поэтому взят MST-вариант. Противоречие: в англ. названии КНС «2P», хотя по индексу 1924 модель 4-портовая; уточнить. Для юрлиц цена с НДС. Статус «официальный дистрибьютор» по сайту aten.ru, подтверждения на aten.com нет.
A12: КВМ | B12: Adder | C12: ADDERView PRO AV4PRO-DP | D12: 73990 | E12: 4 | F12: 2 | G12: 6 | H12: 12 | I12: 3 | J12: 1 | K12: snippet_unverified | L12: https://www.adder.com/en/kvm-solutions/adderviewr-4-pro-displayport | M12: Проверяемой рублёвой цены нет. Справочно, не для РФ: в сниппетах US-магазинов $738–820 (вариант -US); по сниппету CDW снят с продажи 09.06.2026 (не проверено). Сниппет 03.10 с ct-company 73 990 руб. не проверен: страница за антибот-защитой, обход не выполнялся. Статус «эксклюзивный дистрибьютор» kvmtech.ru и «официальный» МАСТ противоречат друг другу.
A13: Коммутаторы | B13: HP (HPE Aruba) | C13: Aruba CX 6100 24G 4SFP+ (JL678A) | D13: 134080 | E13: 5 | F13: 4 | G13: 1 | H13: 12 | I13: 4 | J13: 1 | K13: verified_2026-10-13 | L13: https://www.alianza.ru/kommutator-aruba-6100-jl678a-24g-4sfp/ | M13: Гарантия на странице не указана; официальная гарантия и поддержка HPE в РФ не действуют (Хабр, 10.08.2026). Приказ №4769 код 8517 не меняет, исключение HPE касается 8471 и мониторов 8528 (см. раздел о параллельном импорте). На странице рядом с ценой «0 руб.» без пояснения.
A14: Коммутаторы | B14: Cisco | C14: Catalyst C1000-24T-4X-L | D14: 86209 | E14: 4 | F14: 4 | G14: 1 | H14: 12 | I14: 4 | J14: 1 | K14: verified_2026-10-13 | L14: https://network.msk.ru/products/kommutator_cisco_c100024t4xl | M14: Только L2. Гарантия продавца 1 год «если не оговорено иное»; поддержка Cisco (TAC, ПО) в РФ закрыта. 03.10 у другого продавца (100gigabit.ru) было 49 806,78 без указания НДС: разброс цен большой.
A15: Коммутаторы | B15: Eltex | C15: MES2300-24 | D15: 144916 | E15: 5 | F15: 4 | G15: 3 | H15: 12 | I15: 1 | J15: 4 | K15: snapshot_2026-10-03 | L15: https://etpgpb.ru/portal/catalog/products/2340075-kommutator-dostupa-eltex-mes2300-24-24h10-100-1000base-t-rj-45-4h10/ | M15: 13.10 ЭТП ГПБ недоступна (connection refused), поиск розничной цены не дал результата: у дилеров «по запросу». Цена с закупочной площадки, не розничная, НДС не указан. Реестр ПП 719 заявлен дилером для категории MES в целом, запись по модели не подтверждена. Единственный кандидат с полноценным L3.
... A18: ПК и серверы | B18: HP | C18: HP Elite 800 G9 Mini C7GG7AT + HPE ProLiant DL20 Gen10 4SFF P17081-B21 (1U) | D18: 280177 | E18: 4 | F18: 1 | G18: 12 | H18: 60 | I18: 5 | J18: 1 | K18: verified_2026-10-13 | L18: https://www.kns.ru/catalog/kompyutery/hp/elitedesk/800-g9/ ; https://servermall.ru/sets/server-hpe-proliant-dl20-gen10/ | M18: Сумма = 95 933 (ПК, КНС; НДС на странице каталога не указан) + 184 244 (сервер «от», с НДС 22%; без НДС 151 020). Гарантия 60 мес только на сервер (продавец); на ПК у КНС срок не указан. DL20 Gen10 старше поколением (Xeon E-2200, DDR4), чем SR250 V3 (E-2400, DDR5): прямое сравнение цен некорректно. HP и HPE исключены из перечня параллельного импорта с 27.05.2026 по кодам 8471 49 000 0 и 8471 70; под какой код декларируются мини-ПК и сервер, не проверялось.

Sheet Приоритеты
A1: Локальные приоритеты (Python, собственный вектор матриц парных сравнений альтернатив) и глобальный приоритет (формула)
A2: Глобальный приоритет = Σ w_k · p_k; веса берутся с листа «Критерии», ранг - внутри категории.
A3: Категория | B3: Поставщик | C3: p(k1) | D3: p(k2) | E3: p(k3) | F3: p(k4) | G3: p(k5) | H3: p(k6) | I3: p(k7) | J3: Глобальный приоритет | K3: Ранг в категории
A4: Вес w → | C4: =Критерии!$J$4 -> 0.21314436 | D4: =Критерии!$J$5 -> 0.14945316 | E4: =Критерии!$J$6 -> 0.22208654 | F4: =Критерии!$J$7 -> 0.094914389 | G4: =Критерии!$J$8 -> 0.053684292 | H4: =Критерии!$J$9 -> 0.18218544 | I4: =Критерии!$J$10 -> 0.08453183
A5: ИБП | B5: APC | C5: 0.0773 | D5: 0.375 | E5: 0.1681 | F5: 0.3214 | G5: 0.0769 | H5: 0.0506 | I5: 0.0674 | J5: =C5*C$4+D5*D$4+E5*E$4+F5*F$4+G5*G$4+H5*H$4+I5*I$4 -> 0.15940357 | K5: =COUNTIFS($A$5:$A$19,A5,$J$5:$J$19,">"&J5)+1 -> 4
A6: ИБП | B6: Vertiv | C6: 0.282 | D6: 0.375 | E6: 0.0364 | F6: 0.0357 | G6: 0.3077 | H6: 0.1044 | I6: 0.0674 | J6: =C6*C$4+D6*D$4+E6*E$4+F6*F$4+G6*G$4+H6*H$4+I6*I$4 -> 0.1688603 | K6: =COUNTIFS($A$5:$A$19,A6,$J$5:$J$19,">"&J6)+1 -> 3
A7: ИБП | B7: Eltena | C7: 0.2643 | D7: 0.125 | E7: 0.3977 | F7: 0.3214 | G7: 0.3077 | H7: 0.4225 | I7: 0.2825 | J7: =C7*C$4+D7*D$4+E7*E$4+F7*F$4+G7*G$4+H7*H$4+I7*I$4 -> 0.31121724 | K7: =COUNTIFS($A$5:$A$19,A7,$J$5:$J$19,">"&J7)+1 -> 2
A8: ИБП | B8: Piton | C8: 0.3764 | D8: 0.125 | E8: 0.3977 | F8: 0.3214 | G8: 0.3077 | H8: 0.4225 | I8: 0.5827 | J8: =C8*C$4+D8*D$4+E8*E$4+F8*F$4+G8*G$4+H8*H$4+I8*I$4 -> 0.36048718 | K8: =COUNTIFS($A$5:$A$19,A8,$J$5:$J$19,">"&J8)+1 -> 1
A9: АВР | B9: Elemy | C9: 0.3037 | D9: 0.637 | E9: 0.2 | F9: 0.1818 | G9: 0.5 | H9: 0.3333 | I9: 0.3333 | J9: =C9*C$4+D9*D$4+E9*E$4+F9*F$4+G9*G$4+H9*H$4+I9*I$4 -> 0.33734536 | K9: =COUNTIFS($A$5:$A$19,A9,$J$5:$J$19,">"&J9)+1 -> 2
A10: АВР | B10: Уралэнерготел | C10: 0.4893 | D10: 0.1047 | E10: 0.6 | F10: 0.5455 | G10: 0.25 | H10: 0.3333 | I10: 0.3333 | J10: =C10*C$4+D10*D$4+E10*E$4+F10*F$4+G10*G$4+H10*H$4+I10*I$4 -> 0.40728494 | K10: =COUNTIFS($A$5:$A$19,A10,$J$5:$J$19,">"&J10)+1 -> 1
A11: АВР | B11: BONPET | C11: 0.207 | D11: 0.2583 | E11: 0.2 | F11: 0.2727 | G11: 0.25 | H11: 0.3333 | I11: 0.3333 | J11: =C11*C$4+D11*D$4+E11*E$4+F11*F$4+G11*G$4+H11*H$4+I11*I$4 -> 0.25534303 | K11: =COUNTIFS($A$5:$A$19,A11,$J$5:$J$19,">"&J11)+1 -> 3
A12: КВМ | B12: Aten | C12: 0.5064 | D12: 0.5 | E12: 0.8333 | F12: 0.6667 | G12: 0.5 | H12: 0.75 | I12: 0.5 | J12: =C12*C$4+D12*D$4+E12*E$4+F12*F$4+G12*G$4+H12*H$4+I12*I$4 -> 0.63675415 | K12: =COUNTIFS($A$5:$A$19,A12,$J$5:$J$19,">"&J12)+1 -> 1
A13: КВМ | B13: Adder | C13: 0.4936 | D13: 0.5 | E13: 0.1667 | F13: 0.3333 | G13: 0.5 | H13: 0.25 | I13: 0.5 | J13: =C13*C$4+D13*D$4+E13*E$4+F13*F$4+G13*G$4+H13*H$4+I13*I$4 -> 0.36324585 | K13: =COUNTIFS($A$5:$A$19,A13,$J$5:$J$19,">"&J13)+1 -> 2
A14: Коммутаторы | B14: HP (HPE Aruba) | C14: 0.1163 | D14: 0.3899 | E14: 0.3182 | F14: 0.406 | G14: 0.25 | H14: 0.076 | I14: 0.1 | J14: =C14*C$4+D14*D$4+E14*E$4+F14*F$4+G14*G$4+H14*H$4+I14*I$4 -> 0.227984 | K14: =COUNTIFS($A$5:$A$19,A14,$J$5:$J$19,">"&J14)+1 -> 2
A15: Коммутаторы | B15: Cisco | C15: 0.1809 | D15: 0.1524 | E15: 0.3182 | F15: 0.406 | G15: 0.25 | H15: 0.076 | I15: 0.1 | J15: =C15*C$4+D15*D$4+E15*E$4+F15*F$4+G15*G$4+H15*H$4+I15*I$4 -> 0.206258 | K15: =COUNTIFS($A$5:$A$19,A15,$J$5:$J$19,">"&J15)+1 -> 4
A16: Коммутаторы | B16: Eltex | C16: 0.1076 | D16: 0.3899 | E16: 0.3182 | F16: 0.1458 | G16: 0.25 | H16: 0.657 | I16: 0.7 | J16: =C16*C$4+D16*D$4+E16*E$4+F16*F$4+G16*G$4+H16*H$4+I16*I$4 -> 0.35800176 | K16: =COUNTIFS($A$5:$A$19,A16,$J$5:$J$19,">"&J16)+1 -> 1
... A19: ПК и серверы | B19: HP | C19: 0.6191 | D19: 0.5 | E19: 0.25 | F19: 0.4 | G19: 0.5 | H19: 0.25 | I19: 0.5 | J19: =C19*C$4+D19*D$4+E19*E$4+F19*F$4+G19*G$4+H19*H$4+I19*I$4 -> 0.41482606 | K19: =COUNTIFS($A$5:$A$19,A19,$J$5:$J$19,">"&J19)+1 -> 2

Sheet Пример_ИБП_k1
A1: Пример: матрица парных сравнений ИБП по стоимости (k1, чем дешевле - тем лучше)
A2: a_ij = цена_j / цена_i, ограничено шкалой Саати [1/9; 9]
A4: Поставщик | B4: Цена, ₽ | C4: APC | D4: Vertiv | E4: Eltena | F4: Piton | G4: Ср. геом. | H4: Приоритет | I4: (A·w) | J4: (A·w)/w
A5: APC | B5: =Данные!D4 -> 389565 | C5: =MIN(9,MAX(1/9,$B$5/$B5)) -> 1 | D5: =MIN(9,MAX(1/9,$B$6/$B5)) -> 0.27395685 | E5: =MIN(9,MAX(1/9,$B$7/$B5)) -> 0.29223365 | F5: =MIN(9,MAX(1/9,$B$8/$B5)) -> 0.20522891 | G5: =PRODUCT(C5:F5)^(1/4) -> 0.35802449 | H5: =G5/SUM($G$5:$G$8) -> 0.077251472 | I5: =C5*$H$5+D5*$H$6+E5*$H$7+F5*$H$8 -> 0.30900589 | J5: =I5/H5 -> 4
A6: Vertiv | B6: =Данные!D5 -> 106724 | C6: =MIN(9,MAX(1/9,$B$5/$B6)) -> 3.6502099 | D6: =MIN(9,MAX(1/9,$B$6/$B6)) -> 1 | E6: =MIN(9,MAX(1/9,$B$7/$B6)) -> 1.0667141 | F6: =MIN(9,MAX(1/9,$B$8/$B6)) -> 0.74912859 | G6: =PRODUCT(C6:F6)^(1/4) -> 1.3068645 | H6: =G6/SUM($G$5:$G$8) -> 0.28198409 | I6: =C6*$H$5+D6*$H$6+E6*$H$7+F6*$H$8 -> 1.1279363 | J6: =I6/H6 -> 4
A7: Eltena | B7: =Данные!D6 -> 113844 | C7: =MIN(9,MAX(1/9,$B$5/$B7)) -> 3.4219195 | D7: =MIN(9,MAX(1/9,$B$6/$B7)) -> 0.93745828 | E7: =MIN(9,MAX(1/9,$B$7/$B7)) -> 1 | F7: =MIN(9,MAX(1/9,$B$8/$B7)) -> 0.7022768 | G7: =PRODUCT(C7:F7)^(1/4) -> 1.225131 | H7: =G7/SUM($G$5:$G$8) -> 0.26434831 | I7: =C7*$H$5+D7*$H$6+E7*$H$7+F7*$H$8 -> 1.0573933 | J7: =I7/H7 -> 4
A8: Piton | B8: =Данные!D7 -> 79950 | C8: =MIN(9,MAX(1/9,$B$5/$B8)) -> 4.8726079 | D8: =MIN(9,MAX(1/9,$B$6/$B8)) -> 1.3348843 | E8: =MIN(9,MAX(1/9,$B$7/$B8)) -> 1.42394 | F8: =MIN(9,MAX(1/9,$B$8/$B8)) -> 1 | G8: =PRODUCT(C8:F8)^(1/4) -> 1.7445129 | H8: =G8/SUM($G$5:$G$8) -> 0.37641613 | I8: =C8*$H$5+D8*$H$6+E8*$H$7+F8*$H$8 -> 1.5056645 | J8: =I8/H8 -> 4
A10: λmax | B10: =AVERAGE(J5:J8) -> 4
A11: ИС | B11: =(B10-4)/(4-1) -> 0
A12: СИ | B12: 0.9
A13: ОС | B13: =IF(B12=0,0,B11/B12) -> 0
